codesecdirectagpl3/__init__.py
codesecdirectagpl3/module1.py
codesecdirectagpl3-0.2.0.dist-info/LICENSE
codesecdirectagpl3-0.2.0.dist-info/METADATA
codesecdirectagpl3-0.2.0.dist-info/WHEEL
codesecdirectagpl3-0.2.0.dist-info/top_level.txt
codesecdirectagpl3-0.2.0.dist-info/RECORD
